README.rst
setup.py
epoca_crawler/__init__.py
epoca_crawler/__main__.py
epoca_crawler/epoca_crawler.py
epoca_crawler/extrator.py
epoca_crawler/ferramentas_redes.py
epoca_crawler.egg-info/PKG-INFO
epoca_crawler.egg-info/SOURCES.txt
epoca_crawler.egg-info/dependency_links.txt
epoca_crawler.egg-info/entry_points.txt
epoca_crawler.egg-info/top_level.txt