Metadata-Version: 1.0
Name: epoca-crawler
Version: 0.1
Summary: Ferramenta para extraçao de informaçoes do site epocacosmeticos.com.br.
Home-page: https://github.com/PauloSm/Epoca_Crawler
Author: Paulo Cesar G. Sant'Anna
Author-email: paulo.santanna89@gmail.com
License: UNKNOWN
Platform: UNKNOWN
